Workbook

Sheet Inputs
A1: Inputs: fictional Irish bakery, 800g white sliced pan
A2: Blue = input you can change. Black = formula.
A3: Item | B3: Value | C3: Unit | D3: Source / note
A4: Recipe per loaf
A5: Flour | B5: 480 | C5: g | D5: Assumption: about 60% of dough weight
A6: Butter (fat) | B6: 15 | C6: g | D6: Assumption
A7: Sugar | B7: 10 | C7: g | D7: Assumption
A8: Milk | B8: 30 | C8: ml | D8: Assumption
A9: Other ingredients (yeast, salt, improver) | B9: 0.02 | C9: € per loaf | D9: Assumption
A11: Bakery’s ingredient prices (Sept 2026)
A12: Flour price | B12: 0.6 | C12: € per kg | D12: Assumption: bulk bread flour, illustrative
A13: Butter price | B13: 6 | C13: € per kg | D13: Assumption: bulk butter, illustrative
A14: Sugar price | B14: 0.8 | C14: € per kg | D14: Assumption: bulk sugar, illustrative
A15: Milk price | B15: 0.5 | C15: € per litre | D15: Assumption: bulk milk, illustrative
A17: Other costs per loaf
A18: Packaging | B18: 0.04 | C18: € per loaf | D18: Assumption
A19: Energy (baking) | B19: 0.08 | C19: € per loaf | D19: Assumption
A20: Direct labour | B20: 0.12 | C20: € per loaf | D20: Assumption
A21: Distribution | B21: 0.06 | C21: € per loaf | D21: Assumption
A23: Selling and volume
A24: Latest CSO month | B24: =MAX(CSO_Prices[Month]) -> 46266 | C24: month | D24: CSO_Prices sheet
A25: Shelf price | B25: =_xlfn.XLOOKUP(B24, CSO_Prices[Month], CSO_Prices[Loaf 800g]) -> 1.672 | C25: € per loaf | D25: CSO CPM12, latest month
A26: Retailer margin | B26: 0.25 | C26: % of shelf price | D26: Assumption
A27: VAT rate | B27: 0 | C27: % | D27: Bread is zero-rated in Ireland (see row 45)
A28: Weekly volume | B28: 20000 | C28: loaves | D28: Assumption
A29: Fixed costs | B29: 7000 | C29: € per week | D29: Assumption: rent, salaried staff, equipment
A30: Comparison month | B30: =EDATE(B24,-60) -> 44440 | C30: month | D30: Five years before the latest CSO month
A31: Cost rises since comparison month
A32: Minimum wage, comparison month | B32: 10.2 | C32: € per hour | D32: S.I. 427/2020, from 1 Jan 2021
A33: Minimum wage, latest month | B33: 14.15 | C33: € per hour | D33: National minimum wage from 1 Jan 2026
A34: Labour rise | B34: =B33/B32-1 -> 0.3872549 | C34: % | D34: Minimum wage as proxy
A35: Energy rise | B35: =_xlfn.XLOOKUP($B$24, CPI_Index[Month], CPI_Index[CPI electricity]) / _xlfn.XLOOKUP($B$30, CPI_Index[Month], CPI_Index[CPI electricity]) - 1 -> 0.49850746 | C35: % | D35: CSO CPM24, CPI electricity
A36: Distribution rise | B36: =_xlfn.XLOOKUP($B$24, CPI_Index[Month], CPI_Index[CPI fuels]) / _xlfn.XLOOKUP($B$30, CPI_Index[Month], CPI_Index[CPI fuels]) - 1 -> 0.33523375 | C36: % | D36: CSO CPM24, CPI fuels
A37: Packaging and fixed costs rise | B37: =_xlfn.XLOOKUP($B$24, CPI_Index[Month], CPI_Index[CPI all items]) / _xlfn.XLOOKUP($B$30, CPI_Index[Month], CPI_Index[CPI all items]) - 1 -> 0.23963134 | C37: % | D37: CSO CPM24, CPI all items
A39: Pricing decision
A40: Price change vs CSO shelf price | B40: 0 | C40: % | D40: Set by Goal Seek
A41: Operating margin gap vs comparison month | B41: =Calculations!D35 -> -0.045534485 | C41: % points | D41: Goal Seek target: 0
A43: Checks
A44: Fat + sugar as % of flour | B44: =(B6+B7)/B5 -> 0.052083333 | C44: % | D44: Revenue limit for 0% VAT: 12%
A45: VAT check | B45: =IF(B44<=12%, "OK: zero-rated", "Check: reduced VAT rate applies") -> OK: zero-rated

Sheet Calculations
A1: Calculations: cost, margin and profit per loaf
A2: Formulas only. Change numbers on the Inputs tab.
A3: Item | B3: =Inputs!B24 -> 46266 | C3: =Inputs!B30 -> 44440 | D3: Change | E3: Change % | F3: Unit
A4: CSO shop prices
A5: Loaf 800g | B5: =_xlfn.XLOOKUP(B$3, CSO_Prices[Month], CSO_Prices[Loaf 800g]) -> 1.672 | C5: =_xlfn.XLOOKUP(C$3, CSO_Prices[Month], CSO_Prices[Loaf 800g]) -> 1.364 | D5: =B5-C5 -> 0.308 | E5: =B5/C5-1 -> 0.22580645 | F5: € per loaf
A6: Flour 2kg | B6: =_xlfn.XLOOKUP(B$3, CSO_Prices[Month], CSO_Prices[Flour 2kg]) -> 2.565 | C6: =_xlfn.XLOOKUP(C$3, CSO_Prices[Month], CSO_Prices[Flour 2kg]) -> 2.037 | D6: =B6-C6 -> 0.528 | E6: =B6/C6-1 -> 0.25920471 | F6: € per 2 kg
A7: Butter lb | B7: =_xlfn.XLOOKUP(B$3, CSO_Prices[Month], CSO_Prices[Butter lb]) -> 4.238 | C7: =_xlfn.XLOOKUP(C$3, CSO_Prices[Month], CSO_Prices[Butter lb]) -> 2.975 | D7: =B7-C7 -> 1.263 | E7: =B7/C7-1 -> 0.42453782 | F7: € per lb
A8: Sugar 1kg | B8: =_xlfn.XLOOKUP(B$3, CSO_Prices[Month], CSO_Prices[Sugar 1kg]) -> 1.834 | C8: =_xlfn.XLOOKUP(C$3, CSO_Prices[Month], CSO_Prices[Sugar 1kg]) -> 1.17 | D8: =B8-C8 -> 0.664 | E8: =B8/C8-1 -> 0.56752137 | F8: € per kg
A9: Milk 2L | B9: =_xlfn.XLOOKUP(B$3, CSO_Prices[Month], CSO_Prices[Milk 2L]) -> 2.374 | C9: =_xlfn.XLOOKUP(C$3, CSO_Prices[Month], CSO_Prices[Milk 2L]) -> 1.693 | D9: =B9-C9 -> 0.681 | E9: =B9/C9-1 -> 0.40224454 | F9: € per 2 litres
A11: Bakery’s ingredient cost per loaf
A12: Flour | B12: =Inputs!$B$5/1000*Inputs!$B$12*B6/$B6 -> 0.288 | C12: =Inputs!$B$5/1000*Inputs!$B$12*C6/$B6 -> 0.22871579 | D12: =B12-C12 -> 0.059284211 | E12: =B12/C12-1 -> 0.25920471 | F12: € per loaf
A13: Butter | B13: =Inputs!$B$6/1000*Inputs!$B$13*B7/$B7 -> 0.09 | C13: =Inputs!$B$6/1000*Inputs!$B$13*C7/$B7 -> 0.063178386 | D13: =B13-C13 -> 0.026821614 | E13: =B13/C13-1 -> 0.42453782 | F13: € per loaf
A14: Sugar | B14: =Inputs!$B$7/1000*Inputs!$B$14*B8/$B8 -> 0.008 | C14: =Inputs!$B$7/1000*Inputs!$B$14*C8/$B8 -> 0.0051035987 | D14: =B14-C14 -> 0.0028964013 | E14: =B14/C14-1 -> 0.56752137 | F14: € per loaf
A15: Milk | B15: =Inputs!$B$8/1000*Inputs!$B$15*B9/$B9 -> 0.015 | C15: =Inputs!$B$8/1000*Inputs!$B$15*C9/$B9 -> 0.010697136 | D15: =B15-C15 -> 0.0043028644 | E15: =B15/C15-1 -> 0.40224454 | F15: € per loaf
A16: Other ingredients | B16: =Inputs!$B$9 -> 0.02 | C16: =Inputs!$B$9 -> 0.02 | D16: =B16-C16 -> 0 | E16: =B16/C16-1 -> 0 | F16: € per loaf
A17: Ingredients total | B17: =SUM(B12:B16) -> 0.421 | C17: =SUM(C12:C16) -> 0.32769491 | D17: =B17-C17 -> 0.09330509 | E17: =B17/C17-1 -> 0.28473158 | F17: € per loaf
A19: Other costs per loaf
A20: Packaging, energy, labour, distribution | B20: =SUM(Inputs!$B$18:$B$21) -> 0.3 | C20: =Inputs!$B$18/(1+Inputs!$B$37)+Inputs!$B$19/(1+Inputs!$B$35)+Inputs!$B$20/(1+Inputs!$B$34)+Inputs!$B$21/(1+Inputs!$B$36) -> 0.21709183 | D20: =B20-C20 -> 0.082908169 | E20: =B20/C20-1 -> 0.38190368 | F20: € per loaf
A21: Variable cost per loaf | B21: =B17+B20 -> 0.721 | C21: =C17+C20 -> 0.54478674 | D21: =B21-C21 -> 0.17621326 | E21: =B21/C21-1 -> 0.32345365 | F21: € per loaf
A23: Price and margin per loaf
A24: Shelf price | B24: =B5*(1+Inputs!$B$40) -> 1.672 | C24: =C5 -> 1.364 | D24: =B24-C24 -> 0.308 | E24: =B24/C24-1 -> 0.22580645 | F24: € per loaf
A25: Bakery’s selling price | B25: =B24/(1+Inputs!$B$27)*(1-Inputs!$B$26) -> 1.254 | C25: =C24/(1+Inputs!$B$27)*(1-Inputs!$B$26) -> 1.023 | D25: =B25-C25 -> 0.231 | E25: =B25/C25-1 -> 0.22580645 | F25: € per loaf
A26: Contribution per loaf | B26: =B25-B21 -> 0.533 | C26: =C25-C21 -> 0.47821326 | D26: =B26-C26 -> 0.054786741 | E26: =B26/C26-1 -> 0.1145655 | F26: € per loaf
A27: Contribution margin | B27: =B26/B25 -> 0.42503987 | C27: =C26/C25 -> 0.46746164 | D27: =B27-C27 -> -0.042421769 | F27: % of bakery’s price
A29: Weekly totals
A30: Loaves sold | B30: =Inputs!$B$28 -> 20000 | C30: =Inputs!$B$28 -> 20000 | D30: =B30-C30 -> 0 | E30: =B30/C30-1 -> 0 | F30: loaves
A31: Revenue | B31: =B25*B30 -> 25080 | C31: =C25*C30 -> 20460 | D31: =B31-C31 -> 4620 | E31: =B31/C31-1 -> 0.22580645 | F31: € per week
A32: Contribution | B32: =B26*B30 -> 10660 | C32: =C26*C30 -> 9564.2652 | D32: =B32-C32 -> 1095.7348 | E32: =B32/C32-1 -> 0.1145655 | F32: € per week
A33: Fixed costs | B33: =Inputs!$B$29 -> 7000 | C33: =B33/(1+Inputs!$B$37) -> 5646.8401 | D33: =B33-C33 -> 1353.1599 | E33: =B33/C33-1 -> 0.23963134 | F33: € per week
A34: Operating profit | B34: =B32-B33 -> 3660 | C34: =C32-C33 -> 3917.425 | D34: =B34-C34 -> -257.42503 | E34: =B34/C34-1 -> -0.065712816 | F34: € per week
A35: Operating margin | B35: =B34/B31 -> 0.14593301 | C35: =C34/C31 -> 0.1914675 | D35: =B35-C35 -> -0.045534485 | F35: % of revenue
A36: Break-even volume | B36: =B33/B26 -> 13133.208 | C36: =C33/C26 -> 11808.205 | D36: =B36-C36 -> 1325.0034 | E36: =B36/C36-1 -> 0.1122104 | F36: loaves per week

Sheet Scenarios
A1: Scenarios: weekly profit by price change and further cost rise
A2: Price change is against today’s CSO shelf price. Cost rise applies to all bakery costs. Volume held at Inputs B28.
A4: Price change vs today’s shelf price | C4: 0 | D4: 0.02 | E4: 0.04 | F4: 0.06 | G4: 0.08 | H4: 0.1
A5: Shelf price | C5: =Calculations!$B$5*(1+C4) -> 1.672 | D5: =Calculations!$B$5*(1+D4) -> 1.70544 | E5: =Calculations!$B$5*(1+E4) -> 1.73888 | F5: =Calculations!$B$5*(1+F4) -> 1.77232 | G5: =Calculations!$B$5*(1+G4) -> 1.80576 | H5: =Calculations!$B$5*(1+H4) -> 1.8392
A6: Bakery’s price | C6: =C5/(1+Inputs!$B$27)*(1-Inputs!$B$26) -> 1.254 | D6: =D5/(1+Inputs!$B$27)*(1-Inputs!$B$26) -> 1.27908 | E6: =E5/(1+Inputs!$B$27)*(1-Inputs!$B$26) -> 1.30416 | F6: =F5/(1+Inputs!$B$27)*(1-Inputs!$B$26) -> 1.32924 | G6: =G5/(1+Inputs!$B$27)*(1-Inputs!$B$26) -> 1.35432 | H6: =H5/(1+Inputs!$B$27)*(1-Inputs!$B$26) -> 1.3794
A8: Weekly operating profit (€) | B8: Further cost rise
B9: 0 | C9: =Inputs!$B$28*(C$6-Calculations!$B$21*(1+$B9))-Calculations!$B$33*(1+$B9) -> 3660 | D9: =Inputs!$B$28*(D$6-Calculations!$B$21*(1+$B9))-Calculations!$B$33*(1+$B9) -> 4161.6 | E9: =Inputs!$B$28*(E$6-Calculations!$B$21*(1+$B9))-Calculations!$B$33*(1+$B9) -> 4663.2 | F9: =Inputs!$B$28*(F$6-Calculations!$B$21*(1+$B9))-Calculations!$B$33*(1+$B9) -> 5164.8 | G9: =Inputs!$B$28*(G$6-Calculations!$B$21*(1+$B9))-Calculations!$B$33*(1+$B9) -> 5666.4 | H9: =Inputs!$B$28*(H$6-Calculations!$B$21*(1+$B9))-Calculations!$B$33*(1+$B9) -> 6168
B10: 0.025 | C10: =Inputs!$B$28*(C$6-Calculations!$B$21*(1+$B10))-Calculations!$B$33*(1+$B10) -> 3124.5 | D10: =Inputs!$B$28*(D$6-Calculations!$B$21*(1+$B10))-Calculations!$B$33*(1+$B10) -> 3626.1 | E10: =Inputs!$B$28*(E$6-Calculations!$B$21*(1+$B10))-Calculations!$B$33*(1+$B10) -> 4127.7 | F10: =Inputs!$B$28*(F$6-Calculations!$B$21*(1+$B10))-Calculations!$B$33*(1+$B10) -> 4629.3 | G10: =Inputs!$B$28*(G$6-Calculations!$B$21*(1+$B10))-Calculations!$B$33*(1+$B10) -> 5130.9 | H10: =Inputs!$B$28*(H$6-Calculations!$B$21*(1+$B10))-Calculations!$B$33*(1+$B10) -> 5632.5
B11: 0.05 | C11: =Inputs!$B$28*(C$6-Calculations!$B$21*(1+$B11))-Calculations!$B$33*(1+$B11) -> 2589 | D11: =Inputs!$B$28*(D$6-Calculations!$B$21*(1+$B11))-Calculations!$B$33*(1+$B11) -> 3090.6 | E11: =Inputs!$B$28*(E$6-Calculations!$B$21*(1+$B11))-Calculations!$B$33*(1+$B11) -> 3592.2 | F11: =Inputs!$B$28*(F$6-Calculations!$B$21*(1+$B11))-Calculations!$B$33*(1+$B11) -> 4093.8 | G11: =Inputs!$B$28*(G$6-Calculations!$B$21*(1+$B11))-Calculations!$B$33*(1+$B11) -> 4595.4 | H11: =Inputs!$B$28*(H$6-Calculations!$B$21*(1+$B11))-Calculations!$B$33*(1+$B11) -> 5097
B12: 0.075 | C12: =Inputs!$B$28*(C$6-Calculations!$B$21*(1+$B12))-Calculations!$B$33*(1+$B12) -> 2053.5 | D12: =Inputs!$B$28*(D$6-Calculations!$B$21*(1+$B12))-Calculations!$B$33*(1+$B12) -> 2555.1 | E12: =Inputs!$B$28*(E$6-Calculations!$B$21*(1+$B12))-Calculations!$B$33*(1+$B12) -> 3056.7 | F12: =Inputs!$B$28*(F$6-Calculations!$B$21*(1+$B12))-Calculations!$B$33*(1+$B12) -> 3558.3 | G12: =Inputs!$B$28*(G$6-Calculations!$B$21*(1+$B12))-Calculations!$B$33*(1+$B12) -> 4059.9 | H12: =Inputs!$B$28*(H$6-Calculations!$B$21*(1+$B12))-Calculations!$B$33*(1+$B12) -> 4561.5
B13: 0.1 | C13: =Inputs!$B$28*(C$6-Calculations!$B$21*(1+$B13))-Calculations!$B$33*(1+$B13) -> 1518 | D13: =Inputs!$B$28*(D$6-Calculations!$B$21*(1+$B13))-Calculations!$B$33*(1+$B13) -> 2019.6 | E13: =Inputs!$B$28*(E$6-Calculations!$B$21*(1+$B13))-Calculations!$B$33*(1+$B13) -> 2521.2 | F13: =Inputs!$B$28*(F$6-Calculations!$B$21*(1+$B13))-Calculations!$B$33*(1+$B13) -> 3022.8 | G13: =Inputs!$B$28*(G$6-Calculations!$B$21*(1+$B13))-Calculations!$B$33*(1+$B13) -> 3524.4 | H13: =Inputs!$B$28*(H$6-Calculations!$B$21*(1+$B13))-Calculations!$B$33*(1+$B13) -> 4026
A15: Operating margin | B15: Further cost rise
B16: =B9 -> 0 | C16: =C9/(Inputs!$B$28*C$6) -> 0.14593301 | D16: =D9/(Inputs!$B$28*D$6) -> 0.16267943 | E16: =E9/(Inputs!$B$28*E$6) -> 0.17878174 | F16: =F9/(Inputs!$B$28*F$6) -> 0.19427643 | G16: =G9/(Inputs!$B$28*G$6) -> 0.20919724 | H16: =H9/(Inputs!$B$28*H$6) -> 0.22357547
B17: =B10 -> 0.025 | C17: =C10/(Inputs!$B$28*C$6) -> 0.12458134 | D17: =D10/(Inputs!$B$28*D$6) -> 0.14174641 | E17: =E10/(Inputs!$B$28*E$6) -> 0.15825129 | F17: =F10/(Inputs!$B$28*F$6) -> 0.17413334 | G17: =G10/(Inputs!$B$28*G$6) -> 0.18942717 | H17: =H10/(Inputs!$B$28*H$6) -> 0.20416485
B18: =B11 -> 0.05 | C18: =C11/(Inputs!$B$28*C$6) -> 0.10322967 | D18: =D11/(Inputs!$B$28*D$6) -> 0.1208134 | E18: =E11/(Inputs!$B$28*E$6) -> 0.13772083 | F18: =F11/(Inputs!$B$28*F$6) -> 0.15399025 | G18: =G11/(Inputs!$B$28*G$6) -> 0.1696571 | H18: =H11/(Inputs!$B$28*H$6) -> 0.18475424
B19: =B12 -> 0.075 | C19: =C12/(Inputs!$B$28*C$6) -> 0.08187799 | D19: =D12/(Inputs!$B$28*D$6) -> 0.099880383 | E19: =E12/(Inputs!$B$28*E$6) -> 0.11719038 | F19: =F12/(Inputs!$B$28*F$6) -> 0.13384716 | G19: =G12/(Inputs!$B$28*G$6) -> 0.14988703 | H19: =H12/(Inputs!$B$28*H$6) -> 0.16534363
B20: =B13 -> 0.1 | C20: =C13/(Inputs!$B$28*C$6) -> 0.060526316 | D20: =D13/(Inputs!$B$28*D$6) -> 0.078947368 | E20: =E13/(Inputs!$B$28*E$6) -> 0.096659919 | F20: =F13/(Inputs!$B$28*F$6) -> 0.11370407 | G20: =G13/(Inputs!$B$28*G$6) -> 0.13011696 | H20: =H13/(Inputs!$B$28*H$6) -> 0.14593301
A22: 2021 operating margin (target) | B22: =Calculations!C35 -> 0.1914675

Sheet CSO_Prices
A1: Month | B1: Flour 2kg | C1: Loaf 800g | D1: Milk 2L | E1: Butter lb | F1: Sugar 1kg
A2: 40909 | B2: 2.13 | C2: 1.276 | D2: 1.778 | E2: 2.769 | F2: 1.299
A3: 40940 | B3: 2.146 | C3: 1.275 | D3: 1.775 | E3: 2.771 | F3: 1.337
A4: 40969 | B4: 2.14 | C4: 1.281 | D4: 1.774 | E4: 2.769 | F4: 1.341
A5: 41000 | B5: 2.132 | C5: 1.291 | D5: 1.771 | E5: 2.768 | F5: 1.343
A6: 41030 | B6: 2.132 | C6: 1.306 | D6: 1.773 | E6: 2.778 | F6: 1.342
A7: 41061 | B7: 2.132 | C7: 1.299 | D7: 1.772 | E7: 2.785 | F7: 1.335
A8: 41091 | B8: 2.129 | C8: 1.279 | D8: 1.774 | E8: 2.768 | F8: 1.336
A9: 41122 | B9: 2.131 | C9: 1.269 | D9: 1.774 | E9: 2.735 | F9: 1.34
A10: 41153 | B10: 2.183 | C10: 1.265 | D10: 1.768 | E10: 2.611 | F10: 1.342
A11: 41183 | B11: 2.264 | C11: 1.291 | D11: 1.768 | E11: 2.73 | F11: 1.345
A12: 41214 | B12: 2.318 | C12: 1.28 | D12: 1.77 | E12: 2.732 | F12: 1.345
A13: 41244 | B13: 2.329 | C13: 1.323 | D13: 1.77 | E13: 2.753 | F13: 1.34
... A178: 46266 | B178: 2.565 | C178: 1.672 | D178: 2.374 | E178: 4.238 | F178: 1.834

Sheet CPI_Index
A1: Month | B1: CPI all items | C1: CPI electricity | D1: CPI fuels
A2: 40909 | B2: 81.2 | C2: 47.7 | D2: 87.2
A3: 40940 | B3: 81.9 | C3: 47.7 | D3: 89
A4: 40969 | B4: 82.7 | C4: 47.7 | D4: 91.5
A5: 41000 | B5: 82.8 | C5: 48.1 | D5: 94
A6: 41030 | B6: 82.7 | C6: 49 | D6: 92.9
A7: 41061 | B7: 82.6 | C7: 49 | D7: 90.4
A8: 41091 | B8: 82.5 | C8: 49 | D8: 89
A9: 41122 | B9: 83 | C9: 49 | D9: 92.2
A10: 41153 | B10: 82.9 | C10: 49 | D10: 95
A11: 41183 | B11: 82.8 | C11: 51.8 | D11: 93.7
A12: 41214 | B12: 82.5 | C12: 51.8 | D12: 90.8
A13: 41244 | B13: 82.5 | C13: 51.8 | D13: 89.8
... A178: 46266 | B178: 107.6 | C178: 100.4 | D178: 117.1
